pySQLBuilder/Config.py
pySQLBuilder/Constant.py
pySQLBuilder/QueryBuilder.py
pySQLBuilder/QueryObject.py
pySQLBuilder/QueryTranslator.py
pySQLBuilder/__init__.py
pySQLBuilder/Builder/BaseBuilder.py
pySQLBuilder/Builder/DeleteBuilder.py
pySQLBuilder/Builder/InsertBuilder.py
pySQLBuilder/Builder/SelectBuilder.py
pySQLBuilder/Builder/Structure.py
pySQLBuilder/Builder/UpdateBuilder.py
pySQLBuilder/Builder/__init__.py
pySQLBuilder/Builder/Component/GroupByBuilder.py
pySQLBuilder/Builder/Component/HavingBuilder.py
pySQLBuilder/Builder/Component/JoinBuilder.py
pySQLBuilder/Builder/Component/LimitBuilder.py
pySQLBuilder/Builder/Component/OrderByBuilder.py
pySQLBuilder/Builder/Component/WhereBuilder.py
pySQLBuilder/Builder/Component/__init__.py
pySQLBuilder/Query/BaseQuery.py
pySQLBuilder/Query/Delete.py
pySQLBuilder/Query/Insert.py
pySQLBuilder/Query/Manipulation.py
pySQLBuilder/Query/Select.py
pySQLBuilder/Query/Update.py
pySQLBuilder/Query/__init__.py
pySQLBuilder/Query/Component/Clauses.py
pySQLBuilder/Query/Component/GroupBy.py
pySQLBuilder/Query/Component/Having.py
pySQLBuilder/Query/Component/JoinTable.py
pySQLBuilder/Query/Component/LimitOffset.py
pySQLBuilder/Query/Component/OrderBy.py
pySQLBuilder/Query/Component/Where.py
pySQLBuilder/Query/Component/__init__.py
pySQLBuilder/Structure/Clause.py
pySQLBuilder/Structure/Column.py
pySQLBuilder/Structure/Expression.py
pySQLBuilder/Structure/Join.py
pySQLBuilder/Structure/Limit.py
pySQLBuilder/Structure/Order.py
pySQLBuilder/Structure/Table.py
pySQLBuilder/Structure/Value.py
pySQLBuilder/Structure/__init__.py
pySQLBuilder/Translator/BaseTranslator.py
pySQLBuilder/Translator/GenericTranslator.py
pySQLBuilder/Translator/MySQLTranslator.py
pySQLBuilder/Translator/__init__.py
pySQLBuilder-1.2.0.dist-info/LICENSE
pySQLBuilder-1.2.0.dist-info/METADATA
pySQLBuilder-1.2.0.dist-info/WHEEL
pySQLBuilder-1.2.0.dist-info/top_level.txt
pySQLBuilder-1.2.0.dist-info/RECORD
